<?xml version="1.0" encoding="UTF-8"?>
<addon id="script.module.iptvlib"
       name="IPTV Library"
       version="1.0.1"
       provider-name="Dmitry Vinogradov">
    <requires>
        <import addon="xbmc.python" version="2.24.0"/>
    </requires>
    <extension point="xbmc.python.module" library="lib"/>
    <extension point="xbmc.addon.metadata">
        <assets>
            <icon>resources/skins/Default/media/icon.png</icon>
            <fanart></fanart>
            <screenshot></screenshot>
        </assets>
        <summary lang="en">Common library for IPTV Addons</summary>
        <description lang="en">Common library for IPTV Addons</description>
        <platform>all</platform>
        <license>GNU LESSER GENERAL PUBLIC LICENSE Version 3, June 2007</license>
        <source>https://github.com/dmitry-vinogradov/kodi-iptv-addons</source>
        <news>
[B]v1.0.1[/B] (2018-10-11)[CR]
- Improved error handling[CR]
- Fixed bug in date formatting[CR]
- Added day color bar for EPG entries[CR]
[B]v1.0.0[/B] (2018-10-10)[CR]
- Initial release[CR]
        </news>
    </extension>
</addon>
